CHANGELOG.rst
MANIFEST.in
README.rst
setup.py
src/cuckooapi/__init__.py
src/cuckooapi/api.py
src/cuckooapi/endpoints.py
src/cuckooapi.egg-info/PKG-INFO
src/cuckooapi.egg-info/SOURCES.txt
src/cuckooapi.egg-info/dependency_links.txt
src/cuckooapi.egg-info/not-zip-safe
src/cuckooapi.egg-info/requires.txt
src/cuckooapi.egg-info/top_level.txt