Metadata-Version: 1.1
Name: cuckooapi
Version: 1.0.0
Summary: Cuckoo REST API client for Python.
Home-page: https://github.com/nilp0inter/cuckooapi
Author: Roberto Abdelkader Martínez Pérez
Author-email: robertomartinezp@gmail.com
License: LGPLv3
Keywords: cuckoo api drest
Platform: UNKNOWN
Classifier: Development Status :: 4 - Beta
Classifier: Intended Audience :: Developers
Classifier: License :: OSI Approved :: GNU Lesser General Public License v3 (LGPLv3)
Classifier: Programming Language :: Python :: 2.7
Classifier: Programming Language :: Python :: 3.4
Classifier: Topic :: Security
